simpegEMIP/Base.py
simpegEMIP/DebyeDec.py
simpegEMIP/StoltzMacnae.py
simpegEMIP/StretchedExponential.py
simpegEMIP/__init__.py
simpegEMIP/FDEM/AFEMIP_b.py
simpegEMIP/FDEM/BaseAFEMIP.py
simpegEMIP/FDEM/__init__.py
simpegEMIP/FDEM/Utils/Analytics.py
simpegEMIP/FDEM/Utils/ColeCole.py
simpegEMIP/FDEM/Utils/__init__.py
simpegEMIP/SeogiUtils/BiotSavart.py
simpegEMIP/SeogiUtils/Cole.py
simpegEMIP/SeogiUtils/Convolution.py
simpegEMIP/SeogiUtils/Linarg.py
simpegEMIP/SeogiUtils/LinearIP.py
simpegEMIP/SeogiUtils/MagneticDipoleFields.py
simpegEMIP/SeogiUtils/Mumps.py
simpegEMIP/SeogiUtils/Optimize.py
simpegEMIP/SeogiUtils/PetaInv.py
simpegEMIP/SeogiUtils/Polyfit.py
simpegEMIP/SeogiUtils/View.py
simpegEMIP/SeogiUtils/Weights.py
simpegEMIP/SeogiUtils/__init__.py
simpegEMIP/TDEM/FieldsTDEMIP.py
simpegEMIP/TDEM/PetaInv.py
simpegEMIP/TDEM/ProblemTDEMIP.py
simpegEMIP/TDEM/ProblemTDEMIP_linear.py
simpegEMIP/TDEM/Survey.py
simpegEMIP/TDEM/__init__.py
simpegEMIP/TDEM/getJpol.cpython-36m-darwin.so
simpegEMIP/TDEM/getJpol_py.py
simpegEMIP/TDEM/setup.py
simpegEMIP/TDEM/Utils/ColeCole.py
simpegEMIP/TDEM/Utils/__init__.py
simpegEMIP/TDEM/Utils/misc.py
simpegEMIP-0.0.13.dist-info/DESCRIPTION.rst
simpegEMIP-0.0.13.dist-info/METADATA
simpegEMIP-0.0.13.dist-info/RECORD
simpegEMIP-0.0.13.dist-info/WHEEL
simpegEMIP-0.0.13.dist-info/metadata.json
simpegEMIP-0.0.13.dist-info/top_level.txt
