Metadata-Version: 2.0
Name: simpegEMIP
Version: 0.0.13
Summary: UNKNOWN
Home-page: UNKNOWN
Author: Seogi Kang
Author-email: UNKNOWN
License: UNKNOWN
Platform: UNKNOWN
Requires-Dist: numpy (>=1.7)
Requires-Dist: scipy (>=0.13)
Requires-Dist: setuptools (>=18.0)
Requires-Dist: cython
Requires-Dist: pymatsolver (>=0.1.1)
Requires-Dist: ipython
Requires-Dist: matplotlib
Requires-Dist: properties (>=0.5.2)
Requires-Dist: vectormath (>=0.2.0)
Requires-Dist: SimPEG
Requires-Dist: discretize (>=0.2.0)
Requires-Dist: geoana (>=0.0.4)
Requires-Dist: simpegEM1D
